MANIFEST.in
README.md
setup.py
bin/git-vanity
gitvanity/__init__.py
gitvanity/bad-words-en.csv
gitvanity.egg-info/PKG-INFO
gitvanity.egg-info/SOURCES.txt
gitvanity.egg-info/dependency_links.txt
gitvanity.egg-info/not-zip-safe
gitvanity.egg-info/requires.txt
gitvanity.egg-info/top_level.txt
gitvanity/templates/base.html
gitvanity/templates/index.html
gitvanity/templates/metric.html