Metadata-Version: 1.0
Name: gitvanity
Version: 0.1
Summary: vanity leaderboard for git
Home-page: http://github.com/intuition-app/frontend
Author: Brian Brunner
Author-email: brian@intuition.app
License: MIT
Platform: UNKNOWN
